{
  "weeklyGoals": [
    {
      "id": 1754296890180,
      "title": "ghost detection 처리 논문 조사",
      "subGoals": [
        {
          "id": 1754296890181,
          "title": "논문 10개 간단 정리",
          "completed": true
        },
        {
          "id": 1754296890182,
          "title": "괜찮은 3개 추리기",
          "completed": true
        },
        {
          "id": 1754296890183,
          "title": "[Ghost Target Detection in 3D Radar Data using Point Cloud based Deep Neural Network] 정독 & 정리",
          "completed": false
        },
        {
          "id": 1754454460451,
          "title": "[A Credible and Robust Approach to Ego-Motion Estimation Using an Automotive Radar] 정독 & 정리",
          "completed": false
        }
      ],
      "completed": false,
      "createdAt": "2025-08-04T08:41:30.181Z"
    },
    {
      "id": 1754297023964,
      "title": "[도전학기] 파이썬을 이용한 인문사회과학논문 쓰기",
      "subGoals": [
        {
          "id": 1754297023964,
          "title": "계획서 재체출",
          "completed": false
        },
        {
          "id": 1754449640258,
          "title": "통계적 가설 검증 강의 수강",
          "completed": false
        },
        {
          "id": 1754297023965,
          "title": "한국 관련 데이터 조사",
          "completed": false
        },
        {
          "id": 1754297023966,
          "title": "외국 관련 데이터 조사",
          "completed": false
        },
        {
          "id": 1754297023967,
          "title": "논문 초안 작성",
          "completed": false
        },
        {
          "id": 1754297023969,
          "title": "이번 주 과제",
          "completed": false
        },
        {
          "id": 1754297023968,
          "title": "퀴즈 풀기",
          "completed": false
        }
      ],
      "completed": false,
      "createdAt": "2025-08-04T08:43:43.964Z"
    },
    {
      "id": 1754301636901,
      "title": "독서 모임",
      "subGoals": [
        {
          "id": 1754309415864,
          "title": "F1 PPT 만들기",
          "completed": false
        },
        {
          "id": 1754309415865,
          "title": "F1 PPT 발표 준비",
          "completed": false
        },
        {
          "id": 1754309415867,
          "title": "이기적 유전자 마저 읽기",
          "completed": false
        }
      ],
      "completed": false,
      "createdAt": "2025-08-04T10:00:36.901Z"
    },
    {
      "id": 1754297220995,
      "title": "공학수학1 복습",
      "subGoals": [
        {
          "id": 1754297220995,
          "title": "지난 개념 복습",
          "completed": false
        },
        {
          "id": 1754297220996,
          "title": "11주차 강의 수강",
          "completed": false
        },
        {
          "id": 1754297220997,
          "title": "12주차 강의 수강",
          "completed": false
        },
        {
          "id": 1754297220998,
          "title": "13주차 강의 수강",
          "completed": false
        },
        {
          "id": 1754297220999,
          "title": "14주차 강의 수강",
          "completed": false
        },
        {
          "id": 1754297221000,
          "title": "15주차 강의 수강",
          "completed": false
        },
        {
          "id": 1754297250932,
          "title": "복습용 자료 정리",
          "completed": false
        }
      ],
      "completed": false,
      "createdAt": "2025-08-04T08:47:00.995Z"
    },
    {
      "id": 1754300424776,
      "title": "바텐더 로봇팔 논문 조사 & 모터 선정",
      "subGoals": [
        {
          "id": 1754300424776,
          "title": "비슷한 스펙을 가진 로봇팔 연구 논문 10개 정리",
          "completed": false
        },
        {
          "id": 1754406687397,
          "title": "로봇 하드웨어 오픈소스 검색",
          "completed": false
        }
      ],
      "completed": false,
      "createdAt": "2025-08-04T09:40:24.776Z"
    },
    {
      "id": 1754409292013,
      "title": "고체역학 복습",
      "subGoals": [
        {
          "id": 1754409292013,
          "title": "Week1",
          "completed": false
        },
        {
          "id": 1754409292014,
          "title": "Week 2",
          "completed": false
        },
        {
          "id": 1754409292015,
          "title": "Hw 1",
          "completed": false
        },
        {
          "id": 1754409292016,
          "title": "Hw 2",
          "completed": false
        }
      ],
      "completed": false,
      "createdAt": "2025-08-05T15:54:52.013Z"
    },
    {
      "id": 1754454515947,
      "title": "혁펜하임",
      "subGoals": [
        {
          "id": 1754454515947,
          "title": "<Easy 딥러닝> Ch 1 정독",
          "completed": false
        }
      ],
      "completed": false,
      "createdAt": "2025-08-06T04:28:35.947Z"
    },
    {
      "id": 1754300367517,
      "title": "운동",
      "subGoals": [
        {
          "id": 1754309606510,
          "title": "월-가슴 운동",
          "completed": true
        },
        {
          "id": 1754309606512,
          "title": "월-4.5km 달리기",
          "completed": true
        },
        {
          "id": 1754309606511,
          "title": "화-등 운동",
          "completed": true
        },
        {
          "id": 1754309606513,
          "title": "화- 7km 달리기",
          "completed": false
        },
        {
          "id": 1754309606514,
          "title": "수-하체 운동",
          "completed": false
        },
        {
          "id": 1754309606515,
          "title": "수- 4km 달리기",
          "completed": false
        },
        {
          "id": 1754309606516,
          "title": "목-가슴 운동",
          "completed": false
        },
        {
          "id": 1754309606520,
          "title": "목-2km 달리기",
          "completed": false
        },
        {
          "id": 1754309606517,
          "title": "금-등 운동",
          "completed": false
        },
        {
          "id": 1754309606521,
          "title": "금-2km 달리기",
          "completed": false
        },
        {
          "id": 1754309606518,
          "title": "토-어깨/팔 운동",
          "completed": false
        },
        {
          "id": 1754309606519,
          "title": "토- 9km 달리기",
          "completed": false
        },
        {
          "id": 1754309606522,
          "title": "일- PT",
          "completed": false
        },
        {
          "id": 1754309606523,
          "title": "일- 3km 달리기",
          "completed": false
        }
      ],
      "completed": false,
      "createdAt": "2025-08-04T09:39:27.517Z"
    },
    {
      "id": 1754309463071,
      "title": "Task",
      "subGoals": [
        {
          "id": 1754309463071,
          "title": "노트북 충전선 구매",
          "completed": false
        },
        {
          "id": 1754309463072,
          "title": "자취할 때 필요한 것들 목록 정리",
          "completed": false
        },
        {
          "id": 1754309463073,
          "title": "CV 작성",
          "completed": false
        },
        {
          "id": 1754309463074,
          "title": "서울대 로보틱스 랩실 검색(겨울 인턴)",
          "completed": false
        },
        {
          "id": 1754408775266,
          "title": "구독 내역 정리",
          "completed": false
        },
        {
          "id": 1754449695182,
          "title": "<문화의 수수께끼> 구매",
          "completed": false
        }
      ],
      "completed": false,
      "createdAt": "2025-08-04T12:11:03.071Z"
    }
  ],
  "monthlyGoals": [
    {
      "id": 1754308471936,
      "title": "Lidar & Radar 센서퓨전 논문 10편 정리",
      "subGoals": [
        {
          "id": 1754308471936,
          "title": "논문 1편 정리",
          "completed": false
        },
        {
          "id": 1754308471937,
          "title": "논문 1편 정리(2/10)",
          "completed": false
        },
        {
          "id": 1754308471938,
          "title": "논문 1편 정리 (3/10)",
          "completed": false
        },
        {
          "id": 1754308471939,
          "title": "논문 1편 정리 (4/10)",
          "completed": false
        },
        {
          "id": 1754308471940,
          "title": "논문 1편 정리 ( 5/10)",
          "completed": false
        },
        {
          "id": 1754308471941,
          "title": "논문 1편 정리 (6/10)",
          "completed": false
        },
        {
          "id": 1754308471942,
          "title": "논문 1편 정리 (7/10)",
          "completed": false
        },
        {
          "id": 1754308471943,
          "title": "논문 1편 정리 (8/10)",
          "completed": false
        },
        {
          "id": 1754308471944,
          "title": "논문 1편 정리 (9/10)",
          "completed": false
        },
        {
          "id": 1754308471945,
          "title": "논문 1편 정리 (10/10)",
          "completed": false
        }
      ],
      "completed": false,
      "createdAt": "2025-08-04T11:54:31.936Z"
    },
    {
      "id": 1754297271931,
      "title": "공학수학 1 복습",
      "subGoals": [
        {
          "id": 1754306636751,
          "title": "중간고사 범위",
          "completed": false
        },
        {
          "id": 1754306636753,
          "title": "Convolution",
          "completed": false
        },
        {
          "id": 1754306636752,
          "title": "Laplace Transform",
          "completed": false
        },
        {
          "id": 1754306636754,
          "title": "9~11주차",
          "completed": false
        },
        {
          "id": 1754306636755,
          "title": "12주차",
          "completed": false
        },
        {
          "id": 1754306636756,
          "title": "13주차",
          "completed": false
        },
        {
          "id": 1754306636757,
          "title": "14주차",
          "completed": false
        },
        {
          "id": 1754306636758,
          "title": "15주차",
          "completed": false
        }
      ],
      "completed": false,
      "createdAt": "2025-08-04T08:47:51.931Z"
    },
    {
      "id": 1754297278735,
      "title": "공학수학 2 복습",
      "subGoals": [
        {
          "id": 1754306766583,
          "title": "9주차",
          "completed": false
        },
        {
          "id": 1754306766584,
          "title": "10주차",
          "completed": false
        },
        {
          "id": 1754306766585,
          "title": "11주차",
          "completed": false
        },
        {
          "id": 1754306766586,
          "title": "12주차",
          "completed": false
        },
        {
          "id": 1754306766587,
          "title": "13주차",
          "completed": false
        },
        {
          "id": 1754306766588,
          "title": "14주차",
          "completed": false
        },
        {
          "id": 1754306766589,
          "title": "15주차",
          "completed": false
        }
      ],
      "completed": false,
      "createdAt": "2025-08-04T08:47:58.735Z"
    },
    {
      "id": 1754297310229,
      "title": "바텐더 로봇팔 수동 조작",
      "subGoals": [
        {
          "id": 1754306550194,
          "title": "논문 조사",
          "completed": false
        },
        {
          "id": 1754306550195,
          "title": "모터 선정 & 구매",
          "completed": false
        },
        {
          "id": 1754306550196,
          "title": "하드웨어 설계",
          "completed": false
        },
        {
          "id": 1754306550197,
          "title": "URDF 파일 생성",
          "completed": false
        },
        {
          "id": 1754306550198,
          "title": "ROS2 Gazebo 환경에서 키보드로 수동조작",
          "completed": false
        },
        {
          "id": 1754306550199,
          "title": "하드웨어 조립",
          "completed": false
        },
        {
          "id": 1754306550200,
          "title": "로봇팔 키보드 수동조작",
          "completed": false
        }
      ],
      "completed": false,
      "createdAt": "2025-08-04T08:48:30.229Z"
    },
    {
      "id": 1754306602605,
      "title": "고체역학 공부",
      "subGoals": [
        {
          "id": 1754306602605,
          "title": "1주차",
          "completed": false
        },
        {
          "id": 1754306602606,
          "title": "2주차",
          "completed": false
        },
        {
          "id": 1754306602607,
          "title": "3주차",
          "completed": false
        },
        {
          "id": 1754306602608,
          "title": "4주차",
          "completed": false
        },
        {
          "id": 1754306602609,
          "title": "5주차",
          "completed": false
        },
        {
          "id": 1754306602610,
          "title": "6주차",
          "completed": false
        },
        {
          "id": 1754306602611,
          "title": "7주차",
          "completed": false
        },
        {
          "id": 1754306602612,
          "title": "8주차",
          "completed": false
        },
        {
          "id": 1754306602613,
          "title": "9주차",
          "completed": false
        },
        {
          "id": 1754306602614,
          "title": "10주차",
          "completed": false
        },
        {
          "id": 1754306602615,
          "title": "11주차",
          "completed": false
        },
        {
          "id": 1754306602616,
          "title": "12주차",
          "completed": false
        },
        {
          "id": 1754306602617,
          "title": "13주차",
          "completed": false
        },
        {
          "id": 1754306602618,
          "title": "14주차",
          "completed": false
        },
        {
          "id": 1754306602619,
          "title": "15주차",
          "completed": false
        }
      ],
      "completed": false,
      "createdAt": "2025-08-04T11:23:22.605Z"
    },
    {
      "id": 1754308577827,
      "title": "3권 독서",
      "subGoals": [
        {
          "id": 1754308577827,
          "title": "문화의 수수께끼",
          "completed": false
        },
        {
          "id": 1754308577828,
          "title": "이기적 유전자 마무리",
          "completed": false
        },
        {
          "id": 1754308577829,
          "title": "아비투스",
          "completed": false
        },
        {
          "id": 1754308577830,
          "title": "천문학자는 별을 보지 않는다",
          "completed": false
        }
      ],
      "completed": false,
      "createdAt": "2025-08-04T11:56:17.827Z"
    },
    {
      "id": 1754309768166,
      "title": "기계설계산업기사 실기 인강 완강",
      "subGoals": [],
      "completed": false,
      "createdAt": "2025-08-04T12:16:08.166Z"
    },
    {
      "id": 1754309934648,
      "title": "한석준 말하기 인강",
      "subGoals": [],
      "completed": false,
      "createdAt": "2025-08-04T12:18:54.648Z"
    },
    {
      "id": 1754309951082,
      "title": "TEPS",
      "subGoals": [],
      "completed": false,
      "createdAt": "2025-08-04T12:19:11.082Z"
    },
    {
      "id": 1754377180676,
      "title": "Ansys 유튜브 강의(기계공학expert나보다조금더알뿐]",
      "subGoals": [],
      "completed": false,
      "createdAt": "2025-08-05T06:59:40.676Z"
    },
    {
      "id": 1754384369641,
      "title": "혁펜하임",
      "subGoals": [
        {
          "id": 1754384369641,
          "title": "Easy 딥러닝",
          "completed": false
        },
        {
          "id": 1754384369642,
          "title": "인스톨 파이토치",
          "completed": false
        }
      ],
      "completed": false,
      "createdAt": "2025-08-05T08:59:29.641Z"
    }
  ],
  "thinkBigGoals": [
    {
      "id": 1754380848634,
      "title": "3학년 2학기~4학년 1학기 1저자 논문 3편 작성",
      "startDate": "2025-08-05",
      "endDate": "2026-08-31",
      "subGoals": [
        {
          "id": 1754380848634,
          "title": "강현창 선배님 2저자 논문",
          "completed": false
        },
        {
          "id": 1754380848635,
          "title": "1저자 논문 작성 (1/3)",
          "completed": false
        },
        {
          "id": 1754380848636,
          "title": "1저자 논문 작성 (2/3)",
          "completed": false
        },
        {
          "id": 1754380848637,
          "title": "sci급 1저자 논문 작성 (3/3)",
          "completed": false
        }
      ],
      "completed": false,
      "createdAt": "2025-08-05T08:00:48.634Z"
    },
    {
      "id": 1754380907032,
      "title": "학부 학점 4.0 이상 졸업",
      "startDate": "2025-08-05",
      "endDate": "2027-02-28",
      "subGoals": [
        {
          "id": 1754380907032,
          "title": "3학년 2학기 21학점 4.5",
          "completed": false
        },
        {
          "id": 1754380907033,
          "title": "4학년 1학기 21학점 4.5",
          "completed": false
        },
        {
          "id": 1754380907034,
          "title": "4학년 2학기 21학점 4.5",
          "completed": false
        }
      ],
      "completed": false,
      "createdAt": "2025-08-05T08:01:47.032Z"
    },
    {
      "id": 1754379914089,
      "title": "석사 때 탑티어 논문 3편 작성(3개)  -> 미국박사 합격",
      "startDate": "2025-08-05",
      "endDate": "2028-06-30",
      "subGoals": [
        {
          "id": 1754379914089,
          "title": "탑티어 1저자 논문 작성 (1/3)",
          "completed": false
        },
        {
          "id": 1754379914090,
          "title": "탑티어 1저자 논문 작성 (2/3)",
          "completed": false
        },
        {
          "id": 1754379914091,
          "title": "탑티어 1저자 논문 작성 (3/3)",
          "completed": false
        }
      ],
      "completed": false,
      "createdAt": "2025-08-05T07:45:14.089Z"
    },
    {
      "id": 1754381149744,
      "title": "로봇 5개 만들기",
      "startDate": "2025-08-05",
      "endDate": "2027-02-28",
      "subGoals": [
        {
          "id": 1754381149744,
          "title": "바텐더 로봇팔",
          "completed": false
        },
        {
          "id": 1754381149747,
          "title": "사족보행",
          "completed": false
        },
        {
          "id": 1754381149745,
          "title": "드론",
          "completed": false
        },
        {
          "id": 1754381149748,
          "title": "이족보행",
          "completed": false
        },
        {
          "id": 1754381219943,
          "title": "변형가능 원형이동로봇",
          "completed": false
        }
      ],
      "completed": false,
      "createdAt": "2025-08-05T08:05:49.744Z"
    }
  ],
  "completedTasks": [],
  "motivationItems": [
    {
      "id": 1754299955568,
      "title": "유행 따라, 남들 따라 살면 절대 인정 못 받는 이유 | 김갑진 KAIST 물리학과 교수 | 꿈 도전 성장 | 세바시 1999회",
      "url": "https://www.youtube.com/watch?v=NfanUrcvtVY",
      "type": "youtube",
      "notes": "나는 무조건 남과 달라야 한다. \n경쟁을 한다는 것. 경쟁에서 이길 필요가 없다. 내가 아니더라도 다른 사람이 해줄 거니까. \n남들이 이거 해라. 이거하면 성공한다. 저 사람 말이 맞다는 것을 증명하기 위해 왜 내 인생을 허비해야 하는가?",
      "createdAt": "2025-08-04T09:32:35.568Z"
    },
    {
      "id": 1754378920905,
      "title": " 방사능 때문에 카메라가 꺼진 로봇❓ 인류에 따뜻한 행복을 주는 UCLA 교수 겸 로봇 공학자 '데니스 홍' 자기님 | #유퀴즈온더블럭",
      "url": "https://www.youtube.com/watch?v=6nk6TDU8TXs",
      "type": "youtube",
      "notes": "지금까지 40~50개의 로봇을 만드심; 재난현장, 고속이동 2족, 4족, 암벽 등반, 로봇 손, 소프트 로봇 등등\n\n3족 로봇 ->공원에서 딸의 머리를 땋는 아주머니의 모습을 봄. 머리카락이 다리로 보이게 됨. 여기서 아이디어를 얻음\n\n발루 -> 헬륨 풍선에 다리 달린 로봇. 물 위도 걷고 외줄도 탐. 이족 보행 로봇의 문제점인 잘 넘어지고 느린 문제를 해결하고 싶었다. 자신에게 황당한 질문을 던지면 황당한 대답이 나온다. 여기서 아이디어가 나올 때도 있다. 만약 중력의 방향이 반대라면? 헬륨 풍선을 쓰자. 넘어질 수가 없다!\n\n휴머노이드 로봇 다윈의 기술을 오픈 소스로 공개하였다. 그 결과 전세계 곳곳에서 활용되며 교육용으로 사용되기 시작했다. 왜 수많은 돈과 노력을 들인 기법을 왜 퍼트렸을까? 살면서 만나는 갈림길이 많다. 여기에 봉착했을 때 판단하는 자신만의 비법이 있다. 제일 중요한 것은 가슴에서 나오는 것이다. 스스로에게 이 질문을 하면 답이 항상 나온다. 내가 애초에 이걸 왜 시작했지? 아 연구와 교육을 위해 개발했기 때문에 오픈 소스로 공개하는 게 맞다.\n\n사람을 살리는 기술이 해하는 기술로 바뀌면 어떻게 해야 하는가? 교수님은 무기가 달린 로봇은 절대 만들지 않는다. 내가 안 하면 누군가는 할 것이다. 그러니 내가 조금 더 옳은 방향으로 써야겠다. 결국 윤리의 문제인데, 이것은 기술의 문제가 아닌 쓰는 사람의 문제다. 예를 들어 노벨은 다이너마이트의 악용 사례를 보고, 노벨상을 만드는데 사용했다. 아인슈타인은 핵 반대 운동을 했다. 교수님은 학교에서 학생들과 정기적으로 토론한다. 우리가 개발한 기술이 어떤 영향을 미치는지 토론한다.\n\n목숨을 걸고 후쿠시마 원전을 들어간 적이 있다. 팩봇이라는 로봇을 원전에 투입했다. 방사능 때문에 카메라 센서가 죽고 있었다. 그러다 화면이 다 꺼져버렸다. \n\n시각장애인을 위한 무인자동차 대회가 열렸다. 모두가 부정적이었고, 혼자 참가하게 된 것이다. 불가능하다 말하는 사람들 앞에서 코를 납작하게 해야겠다는 생각을 하게 된 것이다. \n\n저항이 있다는 것은 세상을 바꾼다는 증거야.\n------------------------------------------------------------------------\n정말 감명깊은 영상이다. 기본적인 태도부터가 활기차고 긍정적이고 자신감 넘친다. 그리고 내가 원하는 로봇들을 개발한다. 이 연구실에서 일해보고 싶다. 한국이 아닌 해외에서 저런 사람들과 같이 일해보고 싶고, 배우고 싶다.",
      "createdAt": "2025-08-05T07:28:40.905Z"
    }
  ],
  "studySubjects": [
    {
      "id": 1754302210106,
      "title": "공학수학1",
      "description": "",
      "curriculum": [],
      "createdAt": "2025-08-04T10:10:10.106Z"
    }
  ],
  "events": [
    {
      "id": 1754390734303,
      "date": "2025-08-06",
      "title": "학연생 회의",
      "time": "",
      "description": "",
      "createdAt": "2025-08-05T10:45:34.303Z"
    },
    {
      "id": 1754390812840,
      "date": "2025-08-18",
      "title": "자취방 입주",
      "time": "",
      "description": "",
      "createdAt": "2025-08-05T10:46:52.840Z"
    }
  ],
  "writingNotes": [
    {
      "id": 1754403451829,
      "title": "3학년 2학기",
      "content": "[수업] \n-기계진동학/기계학습원론\n-응용고체역학/CAE&CFD/열유체설계공학실습\n-로봇공학\n-확률및랜덤프로세스/Co-op\n[논문] \n-강현창 선배님 논문(2저자)\n-로봇팔 논문(1저자)\n-도전학기 인문사회과학논문\n[프로젝트] \n-바텐더 로봇팔(논문으로 이어서)\n-이족보행 로봇",
      "createdAt": "2025-08-05T14:17:31.829Z",
      "updatedAt": "2025-08-05T14:23:37.104Z"
    }
  ]
}